django_netjsongraph/__init__.py
django_netjsongraph/admin.py
django_netjsongraph/apps.py
django_netjsongraph/contextmanagers.py
django_netjsongraph/models.py
django_netjsongraph/settings.py
django_netjsongraph/utils.py
django_netjsongraph/api/__init__.py
django_netjsongraph/api/generics.py
django_netjsongraph/api/parsers.py
django_netjsongraph/api/serializers.py
django_netjsongraph/api/urls.py
django_netjsongraph/api/views.py
django_netjsongraph/base/__init__.py
django_netjsongraph/base/admin.py
django_netjsongraph/base/link.py
django_netjsongraph/base/node.py
django_netjsongraph/base/snapshot.py
django_netjsongraph/base/topology.py
django_netjsongraph/fixtures/test_nodes.json
django_netjsongraph/fixtures/test_topologies.json
django_netjsongraph/fixtures/test_users.json
django_netjsongraph/management/__init__.py
django_netjsongraph/management/commands/__init__.py
django_netjsongraph/management/commands/save_snapshot.py
django_netjsongraph/management/commands/update_topology.py
django_netjsongraph/migrations/0001_initial.py
django_netjsongraph/migrations/0002_topology_published.py
django_netjsongraph/migrations/0003_topology_receive_strategy.py
django_netjsongraph/migrations/0004_increased_addresses_maxlength.py
django_netjsongraph/migrations/0005_snapshot.py
django_netjsongraph/migrations/0006_added_openvpn_parser.py
django_netjsongraph/migrations/0007_link_status_changed.py
django_netjsongraph/migrations/0008_create_new_address_field.py
django_netjsongraph/migrations/0009_migrate_addresses_data.py
django_netjsongraph/migrations/0010_remove_old_addresses.py
django_netjsongraph/migrations/__init__.py
django_netjsongraph/static/netjsongraph/css/admin.css
django_netjsongraph/static/netjsongraph/css/style.css
django_netjsongraph/static/netjsongraph/css/lib/jquery-ui.min.css
django_netjsongraph/static/netjsongraph/css/lib/images/ui-icons_444444_256x240.png
django_netjsongraph/static/netjsongraph/css/lib/images/ui-icons_555555_256x240.png
django_netjsongraph-0.6.3.post1.dist-info/LICENSE
django_netjsongraph-0.6.3.post1.dist-info/METADATA
django_netjsongraph-0.6.3.post1.dist-info/WHEEL
django_netjsongraph-0.6.3.post1.dist-info/top_level.txt
django_netjsongraph-0.6.3.post1.dist-info/RECORD
