Metadata-Version: 2.1
Name: django-netjsongraph
Version: 0.6.3.post1
Summary: Reusable django app for collecting and visualizing network topology
Home-page: http://netjson.org
Author: Federico Capoano
Author-email: federico.capoano@gmail.com
License: MIT
Download-URL: https://github.com/interop-dev/django-netjsongraph/releases
Keywords: django,netjson,mesh,networking
Platform: Platform Independent
Classifier: Development Status :: 3 - Alpha
Classifier: Environment :: Web Environment
Classifier: Topic :: Internet :: WWW/HTTP
Classifier: Intended Audience :: Developers
Classifier: License :: OSI Approved :: MIT License
Classifier: Operating System :: OS Independent
Classifier: Framework :: Django
Classifier: Topic :: System :: Networking
Classifier: Programming Language :: Python :: 3
Requires-Dist: django (<3.1,>=2.2)
Requires-Dist: djangorestframework (<3.12,>=3.3)
Requires-Dist: django-model-utils
Requires-Dist: netdiff (<0.8.0,>=0.7.0)
Requires-Dist: openwisp-utils (~=0.5.0)
Requires-Dist: jsonfield (<4.0.0,>=3.1.0)
